<?xml version="1.0"?>
<Lichtsignalsteuerung_Versorgung xmlns="http://www.schlothauer.de/OMTC/LStg_Versorgung"><Datenformat>5</Datenformat><Kopfdaten><Kurzbezeichnung>Example</Kurzbezeichnung><Name>Example</Name><Identifikation><KnotenId><Stadt>SUMO</Stadt><KnotenNummer>1</KnotenNummer></KnotenId><OCITKennung><ZNr>1</ZNr><FNr>1</FNr></OCITKennung><UnitId><UnitNr>1</UnitNr></UnitId></Identifikation><Versorgungsprogramm><Name>LISA+</Name><Version>6.0.0.606</Version></Versorgungsprogramm><Bearbeiter>??</Bearbeiter><KnotenVersionsstand>2017-04-04T15:02:11.963Z</KnotenVersionsstand><Planungsversion>LISA_SUMO</Planungsversion><Maschine>TS-070090N</Maschine></Kopfdaten><DigEingangListe><DigEingang><Bezeichnung>IS2.1</Bezeichnung><ObjNr>1</ObjNr><LetzteAenderung><Bearbeiter>trum_ja</Bearbeiter><Datum>2017-04-04T15:02:11.959Z</Datum></LetzteAenderung><IVDetektor>true</IVDetektor><Bauart>Schleife</Bauart><ZugeordneteSignalgruppe>K2</ZugeordneteSignalgruppe><LoeschSekunde>0</LoeschSekunde><MinBelegungAnfo>0</MinBelegungAnfo><Prellzeit>0</Prellzeit></DigEingang><DigEingang><Bezeichnung>IS2.2</Bezeichnung><ObjNr>2</ObjNr><LetzteAenderung><Bearbeiter>trum_ja</Bearbeiter><Datum>2017-04-04T15:02:11.959Z</Datum></LetzteAenderung><IVDetektor>true</IVDetektor><Bauart>Schleife</Bauart><ZugeordneteSignalgruppe>K2</ZugeordneteSignalgruppe><LoeschSekunde>0</LoeschSekunde><MinBelegungAnfo>0</MinBelegungAnfo><Prellzeit>0</Prellzeit></DigEingang><DigEingang><Bezeichnung>IRD1</Bezeichnung><ObjNr>3</ObjNr><LetzteAenderung><Bearbeiter>trum_ja</Bearbeiter><Datum>2017-04-04T15:02:11.959Z</Datum></LetzteAenderung><IVDetektor>true</IVDetektor><Bauart>Infrarot</Bauart><LoeschSekunde>0</LoeschSekunde><MinBelegungAnfo>0</MinBelegungAnfo><Prellzeit>0</Prellzeit></DigEingang><DigEingang><Bezeichnung>IRD2_1</Bezeichnung><ObjNr>4</ObjNr><LetzteAenderung><Bearbeiter>trum_ja</Bearbeiter><Datum>2017-04-04T15:02:11.959Z</Datum></LetzteAenderung><IVDetektor>true</IVDetektor><Bauart>Infrarot</Bauart><LoeschSekunde>0</LoeschSekunde><MinBelegungAnfo>0</MinBelegungAnfo><Prellzeit>0</Prellzeit></DigEingang><DigEingang><Bezeichnung>IRD2_2</Bezeichnung><ObjNr>5</ObjNr><LetzteAenderung><Bearbeiter>trum_ja</Bearbeiter><Datum>2017-04-04T15:02:11.959Z</Datum></LetzteAenderung><IVDetektor>true</IVDetektor><Bauart>Infrarot</Bauart><LoeschSekunde>0</LoeschSekunde><MinBelegungAnfo>0</MinBelegungAnfo><Prellzeit>0</Prellzeit></DigEingang><DigEingang><Bezeichnung>IRD3</Bezeichnung><ObjNr>6</ObjNr><LetzteAenderung><Bearbeiter>trum_ja</Bearbeiter><Datum>2017-04-04T15:02:11.959Z</Datum></LetzteAenderung><IVDetektor>true</IVDetektor><Bauart>Infrarot</Bauart><LoeschSekunde>0</LoeschSekunde><MinBelegungAnfo>0</MinBelegungAnfo><Prellzeit>0</Prellzeit></DigEingang><DigEingang><Bezeichnung>RD1</Bezeichnung><ObjNr>7</ObjNr><LetzteAenderung><Bearbeiter>trum_ja</Bearbeiter><Datum>2017-04-04T15:02:11.959Z</Datum></LetzteAenderung><IVDetektor>true</IVDetektor><Bauart>Radar</Bauart><LoeschSekunde>0</LoeschSekunde><MinBelegungAnfo>0</MinBelegungAnfo><Prellzeit>0</Prellzeit></DigEingang></DigEingangListe><LogikParameter><ParameterBlock><Bezeichnung>par</Bezeichnung><ElementtypGUID>18B73DCF-9382-4D27-BCCE-DC9AEF709F4B</ElementtypGUID><Struktur><MaxRecordZahl>1</MaxRecordZahl><Parameter><Bezeichnung>maxPh1</Bezeichnung><StandardTyp>float</StandardTyp><fDefault>0</fDefault></Parameter><Parameter><Bezeichnung>maxPh2</Bezeichnung><StandardTyp>float</StandardTyp><fDefault>0</fDefault></Parameter><Parameter><Bezeichnung>maxPh3</Bezeichnung><StandardTyp>float</StandardTyp><fDefault>0</fDefault></Parameter><Parameter><Bezeichnung>minPh1</Bezeichnung><StandardTyp>float</StandardTyp><fDefault>0</fDefault></Parameter><Parameter><Bezeichnung>minPh2</Bezeichnung><StandardTyp>float</StandardTyp><fDefault>0</fDefault></Parameter><Parameter><Bezeichnung>minPh3</Bezeichnung><StandardTyp>float</StandardTyp><fDefault>0</fDefault></Parameter><Parameter><Bezeichnung>ZL_IRD1</Bezeichnung><StandardTyp>float</StandardTyp><fDefault>0</fDefault></Parameter><Parameter><Bezeichnung>ZL_IRD2</Bezeichnung><StandardTyp>float</StandardTyp><fDefault>0</fDefault></Parameter><Parameter><Bezeichnung>ZL_IS2_1</Bezeichnung><StandardTyp>float</StandardTyp><fDefault>0</fDefault></Parameter><Parameter><Bezeichnung>ZL_IS2_2</Bezeichnung><StandardTyp>float</StandardTyp><fDefault>0</fDefault></Parameter><Parameter><Bezeichnung>ZL_RD1</Bezeichnung><StandardTyp>float</StandardTyp><fDefault>0</fDefault></Parameter><Parameter><Bezeichnung>ZL_IRD3</Bezeichnung><StandardTyp>float</StandardTyp><fDefault>0</fDefault></Parameter></Struktur><ParmeterSatz><Bezeichnung>Satz_1</Bezeichnung><SatzNr>1</SatzNr><Record><Wert><Parameter>maxPh1</Parameter><fWert>40</fWert></Wert><Wert><Parameter>maxPh2</Parameter><fWert>35</fWert></Wert><Wert><Parameter>maxPh3</Parameter><fWert>30</fWert></Wert><Wert><Parameter>minPh1</Parameter><fWert>9</fWert></Wert><Wert><Parameter>minPh2</Parameter><fWert>1</fWert></Wert><Wert><Parameter>minPh3</Parameter><fWert>6</fWert></Wert><Wert><Parameter>ZL_IRD1</Parameter><fWert>3</fWert></Wert><Wert><Parameter>ZL_IRD2</Parameter><fWert>3</fWert></Wert><Wert><Parameter>ZL_IS2_1</Parameter><fWert>0</fWert></Wert><Wert><Parameter>ZL_IS2_2</Parameter><fWert>0</fWert></Wert><Wert><Parameter>ZL_RD1</Parameter><fWert>3</fWert></Wert><Wert><Parameter>ZL_IRD3</Parameter><fWert>2</fWert></Wert></Record></ParmeterSatz></ParameterBlock></LogikParameter><Steuergeraet><Zykluszeit>1000</Zykluszeit></Steuergeraet><PhasenListe><Phase><Bezeichnung>Phase 1</Bezeichnung><ObjNr>1</ObjNr><Einschaltphase>true</Einschaltphase><Typ><VA>true</VA><Hand>true</Hand></Typ><PhasenElementeintrag><Signalgruppe>K1</Signalgruppe><Signalbild>gruen</Signalbild></PhasenElementeintrag><PhasenElementeintrag><Signalgruppe>K2</Signalgruppe><Signalbild>rot</Signalbild></PhasenElementeintrag><PhasenElementeintrag><Signalgruppe>K3</Signalgruppe><Signalbild>gruen</Signalbild></PhasenElementeintrag><PhasenElementeintrag><Signalgruppe>KRi2</Signalgruppe><Signalbild>dunkel</Signalbild></PhasenElementeintrag></Phase><Phase><Bezeichnung>Phase 2</Bezeichnung><ObjNr>2</ObjNr><Einschaltphase>false</Einschaltphase><Typ><VA>true</VA><Hand>true</Hand></Typ><PhasenElementeintrag><Signalgruppe>K1</Signalgruppe><Signalbild>rot</Signalbild></PhasenElementeintrag><PhasenElementeintrag><Signalgruppe>K2</Signalgruppe><Signalbild>rot</Signalbild></PhasenElementeintrag><PhasenElementeintrag><Signalgruppe>K3</Signalgruppe><Signalbild>gruen</Signalbild></PhasenElementeintrag><PhasenElementeintrag><Signalgruppe>KRi2</Signalgruppe><Signalbild>gruen</Signalbild></PhasenElementeintrag></Phase><Phase><Bezeichnung>Phase 3</Bezeichnung><ObjNr>3</ObjNr><Einschaltphase>false</Einschaltphase><Typ><VA>true</VA><Hand>true</Hand></Typ><PhasenElementeintrag><Signalgruppe>K1</Signalgruppe><Signalbild>rot</Signalbild></PhasenElementeintrag><PhasenElementeintrag><Signalgruppe>K2</Signalgruppe><Signalbild>gruen</Signalbild></PhasenElementeintrag><PhasenElementeintrag><Signalgruppe>K3</Signalgruppe><Signalbild>rot</Signalbild></PhasenElementeintrag><PhasenElementeintrag><Signalgruppe>KRi2</Signalgruppe><Signalbild>dunkel</Signalbild></PhasenElementeintrag></Phase></PhasenListe><PhasenuebergangListe><Phasenuebergang><Bezeichnung>PÜ 1.2</Bezeichnung><ObjNr>1</ObjNr><LetzteAenderung><Bearbeiter>trum_ja</Bearbeiter><Datum>2017-04-03T13:53:11.261Z</Datum></LetzteAenderung><Startphase>Phase 1</Startphase><Zielphase>Phase 2</Zielphase><Schaltinformation><Dauer>6</Dauer><PUeElement><Signalgruppe>K1</Signalgruppe><StartSignalbild>gruen</StartSignalbild><Schaltzeit><Schaltzeitpunkt>0</Schaltzeitpunkt><ZielSignalbild>rot</ZielSignalbild></Schaltzeit></PUeElement><PUeElement><Signalgruppe>KRi2</Signalgruppe><StartSignalbild>dunkel</StartSignalbild><Schaltzeit><Schaltzeitpunkt>6</Schaltzeitpunkt><ZielSignalbild>gruen</ZielSignalbild></Schaltzeit></PUeElement></Schaltinformation></Phasenuebergang><Phasenuebergang><Bezeichnung>PÜ 1.3</Bezeichnung><ObjNr>4</ObjNr><LetzteAenderung><Bearbeiter>trum_ja</Bearbeiter><Datum>2017-04-03T13:53:27.564Z</Datum></LetzteAenderung><Startphase>Phase 1</Startphase><Zielphase>Phase 3</Zielphase><Schaltinformation><Dauer>6</Dauer><PUeElement><Signalgruppe>K1</Signalgruppe><StartSignalbild>gruen</StartSignalbild><Schaltzeit><Schaltzeitpunkt>0</Schaltzeitpunkt><ZielSignalbild>rot</ZielSignalbild></Schaltzeit></PUeElement><PUeElement><Signalgruppe>K2</Signalgruppe><StartSignalbild>rot</StartSignalbild><Schaltzeit><Schaltzeitpunkt>5</Schaltzeitpunkt><ZielSignalbild>gruen</ZielSignalbild></Schaltzeit></PUeElement><PUeElement><Signalgruppe>K3</Signalgruppe><StartSignalbild>gruen</StartSignalbild><Schaltzeit><Schaltzeitpunkt>0</Schaltzeitpunkt><ZielSignalbild>rot</ZielSignalbild></Schaltzeit></PUeElement></Schaltinformation></Phasenuebergang><Phasenuebergang><Bezeichnung>PÜ 2.3</Bezeichnung><ObjNr>2</ObjNr><LetzteAenderung><Bearbeiter>trum_ja</Bearbeiter><Datum>2015-05-06T06:14:20.226Z</Datum></LetzteAenderung><Startphase>Phase 2</Startphase><Zielphase>Phase 3</Zielphase><Schaltinformation><Dauer>6</Dauer><PUeElement><Signalgruppe>K2</Signalgruppe><StartSignalbild>rot</StartSignalbild><Schaltzeit><Schaltzeitpunkt>5</Schaltzeitpunkt><ZielSignalbild>gruen</ZielSignalbild></Schaltzeit></PUeElement><PUeElement><Signalgruppe>K3</Signalgruppe><StartSignalbild>gruen</StartSignalbild><Schaltzeit><Schaltzeitpunkt>0</Schaltzeitpunkt><ZielSignalbild>rot</ZielSignalbild></Schaltzeit></PUeElement><PUeElement><Signalgruppe>KRi2</Signalgruppe><StartSignalbild>gruen</StartSignalbild><Schaltzeit><Schaltzeitpunkt>6</Schaltzeitpunkt><ZielSignalbild>dunkel</ZielSignalbild></Schaltzeit></PUeElement></Schaltinformation></Phasenuebergang><Phasenuebergang><Bezeichnung>PÜ 3.1</Bezeichnung><ObjNr>3</ObjNr><LetzteAenderung><Bearbeiter>trum_ja</Bearbeiter><Datum>2017-04-03T13:53:51.225Z</Datum></LetzteAenderung><Startphase>Phase 3</Startphase><Zielphase>Phase 1</Zielphase><Schaltinformation><Dauer>7</Dauer><PUeElement><Signalgruppe>K1</Signalgruppe><StartSignalbild>rot</StartSignalbild><Schaltzeit><Schaltzeitpunkt>6</Schaltzeitpunkt><ZielSignalbild>gruen</ZielSignalbild></Schaltzeit></PUeElement><PUeElement><Signalgruppe>K2</Signalgruppe><StartSignalbild>gruen</StartSignalbild><Schaltzeit><Schaltzeitpunkt>0</Schaltzeitpunkt><ZielSignalbild>rot</ZielSignalbild></Schaltzeit></PUeElement><PUeElement><Signalgruppe>K3</Signalgruppe><StartSignalbild>rot</StartSignalbild><Schaltzeit><Schaltzeitpunkt>6</Schaltzeitpunkt><ZielSignalbild>gruen</ZielSignalbild></Schaltzeit></PUeElement></Schaltinformation></Phasenuebergang></PhasenuebergangListe><PhasenuebergangsmatrixListe><Phasenuebergangsmatrix><Bezeichnung>Plan1</Bezeichnung><ObjNr>1</ObjNr><Uebergang><VonPhase>Phase 1</VonPhase><NachPhase>Phase 2</NachPhase></Uebergang><Uebergang><VonPhase>Phase 1</VonPhase><NachPhase>Phase 3</NachPhase></Uebergang><Uebergang><VonPhase>Phase 2</VonPhase><NachPhase>Phase 3</NachPhase></Uebergang><Uebergang><VonPhase>Phase 3</VonPhase><NachPhase>Phase 1</NachPhase></Uebergang></Phasenuebergangsmatrix></PhasenuebergangsmatrixListe><Schaltuhr><TagesplanListe><StandardTagesplan><Bezeichnung>Standard</Bezeichnung><ObjNr>1</ObjNr><LetzteAenderung><Bearbeiter>trum_ja</Bearbeiter><Datum>2017-04-04T15:02:38.902Z</Datum></LetzteAenderung></StandardTagesplan></TagesplanListe><WochenplanListe><StandardWochenplan><Bezeichnung>Standard</Bezeichnung><Tagesplan_Mo>Standard</Tagesplan_Mo><Tagesplan_Di>Standard</Tagesplan_Di><Tagesplan_Mi>Standard</Tagesplan_Mi><Tagesplan_Do>Standard</Tagesplan_Do><Tagesplan_Fr>Standard</Tagesplan_Fr><Tagesplan_Sa>Standard</Tagesplan_Sa><Tagesplan_So>Standard</Tagesplan_So></StandardWochenplan></WochenplanListe></Schaltuhr><Signalgeber><Signalgeberliste><Signalgeber><Bezeichnung>K1</Bezeichnung><SgrBezeichnung>K1</SgrBezeichnung><Mast><Bezeichnung>-</Bezeichnung><Anbringung>Grundmast</Anbringung></Mast></Signalgeber><Signalgeber><Bezeichnung>K2</Bezeichnung><SgrBezeichnung>K2</SgrBezeichnung><Mast><Bezeichnung>-</Bezeichnung><Anbringung>Grundmast</Anbringung></Mast></Signalgeber><Signalgeber><Bezeichnung>K3</Bezeichnung><SgrBezeichnung>K3</SgrBezeichnung><Mast><Bezeichnung>-</Bezeichnung><Anbringung>Grundmast</Anbringung></Mast></Signalgeber><Signalgeber><Bezeichnung>KRi2</Bezeichnung><SgrBezeichnung>KRi2</SgrBezeichnung><Mast><Bezeichnung>-</Bezeichnung><Anbringung>Grundmast</Anbringung></Mast></Signalgeber></Signalgeberliste></Signalgeber><SignalgruppeListe><Signalgruppe><Bezeichnung>K1</Bezeichnung><ObjNr>1</ObjNr><Teilknoten>TK 1</Teilknoten><LiegtInVorfahrt>true</LiegtInVorfahrt><VerhaltenBeiNebenrichtungGelbblinken>StandardDunkel</VerhaltenBeiNebenrichtungGelbblinken><ErlaubteSignalbilder><Frei><Standard>gruen</Standard><Zusaetzlich>dunkel</Zusaetzlich><Zusaetzlich>gelbblk</Zusaetzlich></Frei><Gesperrt><Standard>rot</Standard><Zusaetzlich>gelb</Zusaetzlich><Zusaetzlich>rotgelb</Zusaetzlich></Gesperrt><StandardAusDunkel>dunkel</StandardAusDunkel><StandardGelbblinken>dunkel</StandardGelbblinken></ErlaubteSignalbilder><MinFrei>5</MinFrei><MinGesperrt>1</MinGesperrt><AnwurfUebergang><Uebergangselement><Signalbild>rotgelb</Signalbild><Zeitdauer>1</Zeitdauer></Uebergangselement></AnwurfUebergang><AbwurfUebergang><Uebergangselement><Signalbild>gelb</Signalbild><Zeitdauer>3</Zeitdauer></Uebergangselement></AbwurfUebergang><ZusatzUebergang><Bezeichnung>rot_1srotgelb_gruen</Bezeichnung><StartFarbbild>rot</StartFarbbild><ZielFarbbild>gruen</ZielFarbbild><Uebergang><Uebergangselement><Signalbild>rotgelb</Signalbild><Zeitdauer>1</Zeitdauer></Uebergangselement></Uebergang></ZusatzUebergang><ZusatzUebergang><Bezeichnung>rot_2srotgelb_gruen</Bezeichnung><StartFarbbild>rot</StartFarbbild><ZielFarbbild>gruen</ZielFarbbild><Uebergang><Uebergangselement><Signalbild>rotgelb</Signalbild><Zeitdauer>2</Zeitdauer></Uebergangselement></Uebergang></ZusatzUebergang><ZusatzUebergang><Bezeichnung>gruen_3sgelb_rot</Bezeichnung><StartFarbbild>gruen</StartFarbbild><ZielFarbbild>rot</ZielFarbbild><Uebergang><Uebergangselement><Signalbild>gelb</Signalbild><Zeitdauer>3</Zeitdauer></Uebergangselement></Uebergang></ZusatzUebergang><ZusatzUebergang><Bezeichnung>gruen_4sgelb_rot</Bezeichnung><StartFarbbild>gruen</StartFarbbild><ZielFarbbild>rot</ZielFarbbild><Uebergang><Uebergangselement><Signalbild>gelb</Signalbild><Zeitdauer>4</Zeitdauer></Uebergangselement></Uebergang></ZusatzUebergang><ZusatzUebergang><Bezeichnung>gruen_5sgelb_rot</Bezeichnung><StartFarbbild>gruen</StartFarbbild><ZielFarbbild>rot</ZielFarbbild><Uebergang><Uebergangselement><Signalbild>gelb</Signalbild><Zeitdauer>5</Zeitdauer></Uebergangselement></Uebergang></ZusatzUebergang><ZusatzUebergang><Bezeichnung>rot_dunkel</Bezeichnung><StartFarbbild>rot</StartFarbbild><ZielFarbbild>dunkel</ZielFarbbild></ZusatzUebergang><ZusatzUebergang><Bezeichnung>rot_gelbblk</Bezeichnung><StartFarbbild>rot</StartFarbbild><ZielFarbbild>gelbblk</ZielFarbbild></ZusatzUebergang><ZusatzUebergang><Bezeichnung>gruen_dunkel</Bezeichnung><StartFarbbild>gruen</StartFarbbild><ZielFarbbild>dunkel</ZielFarbbild></ZusatzUebergang><ZusatzUebergang><Bezeichnung>gruen_gelbblk</Bezeichnung><StartFarbbild>gruen</StartFarbbild><ZielFarbbild>gelbblk</ZielFarbbild></ZusatzUebergang><ZusatzUebergang><Bezeichnung>dunkel_5sgelb_rot</Bezeichnung><StartFarbbild>dunkel</StartFarbbild><ZielFarbbild>rot</ZielFarbbild><Uebergang><Uebergangselement><Signalbild>gelb</Signalbild><Zeitdauer>5</Zeitdauer></Uebergangselement></Uebergang></ZusatzUebergang><ZusatzUebergang><Bezeichnung>dunkel_gruen</Bezeichnung><StartFarbbild>dunkel</StartFarbbild><ZielFarbbild>gruen</ZielFarbbild></ZusatzUebergang><ZusatzUebergang><Bezeichnung>gelbblk_5sgelb_rot</Bezeichnung><StartFarbbild>gelbblk</StartFarbbild><ZielFarbbild>rot</ZielFarbbild><Uebergang><Uebergangselement><Signalbild>gelb</Signalbild><Zeitdauer>5</Zeitdauer></Uebergangselement></Uebergang></ZusatzUebergang><ZusatzUebergang><Bezeichnung>gelbblk_gruen</Bezeichnung><StartFarbbild>gelbblk</StartFarbbild><ZielFarbbild>gruen</ZielFarbbild></ZusatzUebergang><Ansteuerung><Rot/><Gelb/><Gruen/></Ansteuerung></Signalgruppe><Signalgruppe><Bezeichnung>K2</Bezeichnung><ObjNr>2</ObjNr><Teilknoten>TK 1</Teilknoten><LiegtInVorfahrt>false</LiegtInVorfahrt><VerhaltenBeiNebenrichtungGelbblinken>StandardGelbblinken</VerhaltenBeiNebenrichtungGelbblinken><ErlaubteSignalbilder><Frei><Standard>gruen</Standard></Frei><Gesperrt><Standard>rot</Standard><Zusaetzlich>dunkel</Zusaetzlich><Zusaetzlich>gelb</Zusaetzlich><Zusaetzlich>rotgelb</Zusaetzlich><Zusaetzlich>gelbblk</Zusaetzlich></Gesperrt><StandardAusDunkel>dunkel</StandardAusDunkel><StandardGelbblinken>gelbblk</StandardGelbblinken></ErlaubteSignalbilder><MinFrei>6</MinFrei><MinGesperrt>1</MinGesperrt><AnwurfUebergang><Uebergangselement><Signalbild>rotgelb</Signalbild><Zeitdauer>1</Zeitdauer></Uebergangselement></AnwurfUebergang><AbwurfUebergang><Uebergangselement><Signalbild>gelb</Signalbild><Zeitdauer>3</Zeitdauer></Uebergangselement></AbwurfUebergang><ZusatzUebergang><Bezeichnung>rot_1srotgelb_gruen</Bezeichnung><StartFarbbild>rot</StartFarbbild><ZielFarbbild>gruen</ZielFarbbild><Uebergang><Uebergangselement><Signalbild>rotgelb</Signalbild><Zeitdauer>1</Zeitdauer></Uebergangselement></Uebergang></ZusatzUebergang><ZusatzUebergang><Bezeichnung>rot_2srotgelb_gruen</Bezeichnung><StartFarbbild>rot</StartFarbbild><ZielFarbbild>gruen</ZielFarbbild><Uebergang><Uebergangselement><Signalbild>rotgelb</Signalbild><Zeitdauer>2</Zeitdauer></Uebergangselement></Uebergang></ZusatzUebergang><ZusatzUebergang><Bezeichnung>gruen_3sgelb_rot</Bezeichnung><StartFarbbild>gruen</StartFarbbild><ZielFarbbild>rot</ZielFarbbild><Uebergang><Uebergangselement><Signalbild>gelb</Signalbild><Zeitdauer>3</Zeitdauer></Uebergangselement></Uebergang></ZusatzUebergang><ZusatzUebergang><Bezeichnung>gruen_4sgelb_rot</Bezeichnung><StartFarbbild>gruen</StartFarbbild><ZielFarbbild>rot</ZielFarbbild><Uebergang><Uebergangselement><Signalbild>gelb</Signalbild><Zeitdauer>4</Zeitdauer></Uebergangselement></Uebergang></ZusatzUebergang><ZusatzUebergang><Bezeichnung>gruen_5sgelb_rot</Bezeichnung><StartFarbbild>gruen</StartFarbbild><ZielFarbbild>rot</ZielFarbbild><Uebergang><Uebergangselement><Signalbild>gelb</Signalbild><Zeitdauer>5</Zeitdauer></Uebergangselement></Uebergang></ZusatzUebergang><ZusatzUebergang><Bezeichnung>rot_dunkel</Bezeichnung><StartFarbbild>rot</StartFarbbild><ZielFarbbild>dunkel</ZielFarbbild></ZusatzUebergang><ZusatzUebergang><Bezeichnung>rot_gelbblk</Bezeichnung><StartFarbbild>rot</StartFarbbild><ZielFarbbild>gelbblk</ZielFarbbild></ZusatzUebergang><ZusatzUebergang><Bezeichnung>gruen_dunkel</Bezeichnung><StartFarbbild>gruen</StartFarbbild><ZielFarbbild>dunkel</ZielFarbbild></ZusatzUebergang><ZusatzUebergang><Bezeichnung>gruen_gelbblk</Bezeichnung><StartFarbbild>gruen</StartFarbbild><ZielFarbbild>gelbblk</ZielFarbbild></ZusatzUebergang><ZusatzUebergang><Bezeichnung>dunkel_5sgelb_rot</Bezeichnung><StartFarbbild>dunkel</StartFarbbild><ZielFarbbild>rot</ZielFarbbild><Uebergang><Uebergangselement><Signalbild>gelb</Signalbild><Zeitdauer>5</Zeitdauer></Uebergangselement></Uebergang></ZusatzUebergang><ZusatzUebergang><Bezeichnung>dunkel_gruen</Bezeichnung><StartFarbbild>dunkel</StartFarbbild><ZielFarbbild>gruen</ZielFarbbild></ZusatzUebergang><ZusatzUebergang><Bezeichnung>gelbblk_5sgelb_rot</Bezeichnung><StartFarbbild>gelbblk</StartFarbbild><ZielFarbbild>rot</ZielFarbbild><Uebergang><Uebergangselement><Signalbild>gelb</Signalbild><Zeitdauer>5</Zeitdauer></Uebergangselement></Uebergang></ZusatzUebergang><ZusatzUebergang><Bezeichnung>gelbblk_gruen</Bezeichnung><StartFarbbild>gelbblk</StartFarbbild><ZielFarbbild>gruen</ZielFarbbild></ZusatzUebergang><Ansteuerung><Rot/><Gelb/><Gruen/></Ansteuerung></Signalgruppe><Signalgruppe><Bezeichnung>K3</Bezeichnung><ObjNr>3</ObjNr><Teilknoten>TK 1</Teilknoten><LiegtInVorfahrt>true</LiegtInVorfahrt><VerhaltenBeiNebenrichtungGelbblinken>StandardDunkel</VerhaltenBeiNebenrichtungGelbblinken><ErlaubteSignalbilder><Frei><Standard>gruen</Standard><Zusaetzlich>dunkel</Zusaetzlich><Zusaetzlich>gelbblk</Zusaetzlich></Frei><Gesperrt><Standard>rot</Standard><Zusaetzlich>gelb</Zusaetzlich><Zusaetzlich>rotgelb</Zusaetzlich></Gesperrt><StandardAusDunkel>dunkel</StandardAusDunkel><StandardGelbblinken>dunkel</StandardGelbblinken></ErlaubteSignalbilder><MinFrei>5</MinFrei><MinGesperrt>1</MinGesperrt><AnwurfUebergang><Uebergangselement><Signalbild>rotgelb</Signalbild><Zeitdauer>1</Zeitdauer></Uebergangselement></AnwurfUebergang><AbwurfUebergang><Uebergangselement><Signalbild>gelb</Signalbild><Zeitdauer>3</Zeitdauer></Uebergangselement></AbwurfUebergang><ZusatzUebergang><Bezeichnung>rot_1srotgelb_gruen</Bezeichnung><StartFarbbild>rot</StartFarbbild><ZielFarbbild>gruen</ZielFarbbild><Uebergang><Uebergangselement><Signalbild>rotgelb</Signalbild><Zeitdauer>1</Zeitdauer></Uebergangselement></Uebergang></ZusatzUebergang><ZusatzUebergang><Bezeichnung>rot_2srotgelb_gruen</Bezeichnung><StartFarbbild>rot</StartFarbbild><ZielFarbbild>gruen</ZielFarbbild><Uebergang><Uebergangselement><Signalbild>rotgelb</Signalbild><Zeitdauer>2</Zeitdauer></Uebergangselement></Uebergang></ZusatzUebergang><ZusatzUebergang><Bezeichnung>gruen_3sgelb_rot</Bezeichnung><StartFarbbild>gruen</StartFarbbild><ZielFarbbild>rot</ZielFarbbild><Uebergang><Uebergangselement><Signalbild>gelb</Signalbild><Zeitdauer>3</Zeitdauer></Uebergangselement></Uebergang></ZusatzUebergang><ZusatzUebergang><Bezeichnung>gruen_4sgelb_rot</Bezeichnung><StartFarbbild>gruen</StartFarbbild><ZielFarbbild>rot</ZielFarbbild><Uebergang><Uebergangselement><Signalbild>gelb</Signalbild><Zeitdauer>4</Zeitdauer></Uebergangselement></Uebergang></ZusatzUebergang><ZusatzUebergang><Bezeichnung>gruen_5sgelb_rot</Bezeichnung><StartFarbbild>gruen</StartFarbbild><ZielFarbbild>rot</ZielFarbbild><Uebergang><Uebergangselement><Signalbild>gelb</Signalbild><Zeitdauer>5</Zeitdauer></Uebergangselement></Uebergang></ZusatzUebergang><ZusatzUebergang><Bezeichnung>rot_dunkel</Bezeichnung><StartFarbbild>rot</StartFarbbild><ZielFarbbild>dunkel</ZielFarbbild></ZusatzUebergang><ZusatzUebergang><Bezeichnung>rot_gelbblk</Bezeichnung><StartFarbbild>rot</StartFarbbild><ZielFarbbild>gelbblk</ZielFarbbild></ZusatzUebergang><ZusatzUebergang><Bezeichnung>gruen_dunkel</Bezeichnung><StartFarbbild>gruen</StartFarbbild><ZielFarbbild>dunkel</ZielFarbbild></ZusatzUebergang><ZusatzUebergang><Bezeichnung>gruen_gelbblk</Bezeichnung><StartFarbbild>gruen</StartFarbbild><ZielFarbbild>gelbblk</ZielFarbbild></ZusatzUebergang><ZusatzUebergang><Bezeichnung>dunkel_5sgelb_rot</Bezeichnung><StartFarbbild>dunkel</StartFarbbild><ZielFarbbild>rot</ZielFarbbild><Uebergang><Uebergangselement><Signalbild>gelb</Signalbild><Zeitdauer>5</Zeitdauer></Uebergangselement></Uebergang></ZusatzUebergang><ZusatzUebergang><Bezeichnung>dunkel_gruen</Bezeichnung><StartFarbbild>dunkel</StartFarbbild><ZielFarbbild>gruen</ZielFarbbild></ZusatzUebergang><ZusatzUebergang><Bezeichnung>gelbblk_5sgelb_rot</Bezeichnung><StartFarbbild>gelbblk</StartFarbbild><ZielFarbbild>rot</ZielFarbbild><Uebergang><Uebergangselement><Signalbild>gelb</Signalbild><Zeitdauer>5</Zeitdauer></Uebergangselement></Uebergang></ZusatzUebergang><ZusatzUebergang><Bezeichnung>gelbblk_gruen</Bezeichnung><StartFarbbild>gelbblk</StartFarbbild><ZielFarbbild>gruen</ZielFarbbild></ZusatzUebergang><Ansteuerung><Rot/><Gelb/><Gruen/></Ansteuerung></Signalgruppe><Signalgruppe><Bezeichnung>KRi2</Bezeichnung><ObjNr>4</ObjNr><Teilknoten>TK 1</Teilknoten><LiegtInVorfahrt>false</LiegtInVorfahrt><VerhaltenBeiNebenrichtungGelbblinken>StandardDunkel</VerhaltenBeiNebenrichtungGelbblinken><ErlaubteSignalbilder><Frei><Standard>gruen</Standard></Frei><Gesperrt><Standard>dunkel</Standard><Zusaetzlich>gelb</Zusaetzlich></Gesperrt><StandardAusDunkel>dunkel</StandardAusDunkel><StandardGelbblinken>dunkel</StandardGelbblinken></ErlaubteSignalbilder><MinFrei>5</MinFrei><MinGesperrt>0</MinGesperrt><AbwurfUebergang><Uebergangselement><Signalbild>gelb</Signalbild><Zeitdauer>3</Zeitdauer></Uebergangselement></AbwurfUebergang><ZusatzUebergang><Bezeichnung>dunkel_gruen</Bezeichnung><StartFarbbild>dunkel</StartFarbbild><ZielFarbbild>gruen</ZielFarbbild></ZusatzUebergang><ZusatzUebergang><Bezeichnung>gruen_3sgelb_dunkel</Bezeichnung><StartFarbbild>gruen</StartFarbbild><ZielFarbbild>dunkel</ZielFarbbild><Uebergang><Uebergangselement><Signalbild>gelb</Signalbild><Zeitdauer>3</Zeitdauer></Uebergangselement></Uebergang></ZusatzUebergang><ZusatzUebergang><Bezeichnung>gruen_4sgelb_dunkel</Bezeichnung><StartFarbbild>gruen</StartFarbbild><ZielFarbbild>dunkel</ZielFarbbild><Uebergang><Uebergangselement><Signalbild>gelb</Signalbild><Zeitdauer>4</Zeitdauer></Uebergangselement></Uebergang></ZusatzUebergang><ZusatzUebergang><Bezeichnung>gruen_5sgelb_dunkel</Bezeichnung><StartFarbbild>gruen</StartFarbbild><ZielFarbbild>dunkel</ZielFarbbild><Uebergang><Uebergangselement><Signalbild>gelb</Signalbild><Zeitdauer>5</Zeitdauer></Uebergangselement></Uebergang></ZusatzUebergang><Ansteuerung><Gelb/><Gruen/></Ansteuerung></Signalgruppe></SignalgruppeListe><SignalprogrammListe><Signalprogramm><Bezeichnung>SP 1 FZS Spitzenverkehr (90 s)</Bezeichnung><ObjNr>1</ObjNr><LetzteAenderung><Bearbeiter>trum_ja</Bearbeiter><Datum>2015-05-05T13:36:40.854Z</Datum></LetzteAenderung><Versatzzeitenmatrix>VMFA</Versatzzeitenmatrix><Versatzzeitenmatrix>VMFE</Versatzzeitenmatrix><OeVParameter>P1</OeVParameter><Typ><FZ>true</FZ><VA>false</VA></Typ><TU>90</TU><EP>5</EP><AP>7</AP><UP>6</UP><SignalzeitenVersatz>0</SignalzeitenVersatz><EProgramm>EP1 (22 s)</EProgramm><AProgramm>AP1 (26 s)</AProgramm><SPZeile><Signalgruppe>K1</Signalgruppe><Schaltzeit><Schaltzeitpunkt>32</Schaltzeitpunkt><ZielSignalbild>rot</ZielSignalbild></Schaltzeit><Schaltzeit><Schaltzeitpunkt>88</Schaltzeitpunkt><ZielSignalbild>gruen</ZielSignalbild></Schaltzeit></SPZeile><SPZeile><Signalgruppe>K2</Signalgruppe><Schaltzeit><Schaltzeitpunkt>63</Schaltzeitpunkt><ZielSignalbild>gruen</ZielSignalbild></Schaltzeit><Schaltzeit><Schaltzeitpunkt>82</Schaltzeitpunkt><ZielSignalbild>rot</ZielSignalbild></Schaltzeit></SPZeile><SPZeile><Signalgruppe>K3</Signalgruppe><Schaltzeit><Schaltzeitpunkt>58</Schaltzeitpunkt><ZielSignalbild>rot</ZielSignalbild></Schaltzeit><Schaltzeit><Schaltzeitpunkt>88</Schaltzeitpunkt><ZielSignalbild>gruen</ZielSignalbild></Schaltzeit></SPZeile><SPZeile><Signalgruppe>KRi2</Signalgruppe><Schaltzeit><Schaltzeitpunkt>38</Schaltzeitpunkt><ZielSignalbild>gruen</ZielSignalbild></Schaltzeit><Schaltzeit><Schaltzeitpunkt>64</Schaltzeitpunkt><ZielSignalbild>dunkel</ZielSignalbild></Schaltzeit></SPZeile></Signalprogramm><Signalprogramm><Bezeichnung>SP 2 FZS Tagesverkehr (72 s)</Bezeichnung><ObjNr>2</ObjNr><LetzteAenderung><Bearbeiter>trum_ja</Bearbeiter><Datum>2015-05-05T13:49:35.340Z</Datum></LetzteAenderung><Versatzzeitenmatrix>VMFA</Versatzzeitenmatrix><Versatzzeitenmatrix>VMFE</Versatzzeitenmatrix><OeVParameter>P1</OeVParameter><Typ><FZ>true</FZ><VA>false</VA></Typ><TU>72</TU><EP>5</EP><AP>7</AP><UP>6</UP><SignalzeitenVersatz>0</SignalzeitenVersatz><EProgramm>EP1 (22 s)</EProgramm><AProgramm>AP1 (26 s)</AProgramm><SPZeile><Signalgruppe>K1</Signalgruppe><Schaltzeit><Schaltzeitpunkt>14</Schaltzeitpunkt><ZielSignalbild>rot</ZielSignalbild></Schaltzeit><Schaltzeit><Schaltzeitpunkt>70</Schaltzeitpunkt><ZielSignalbild>gruen</ZielSignalbild></Schaltzeit></SPZeile><SPZeile><Signalgruppe>K2</Signalgruppe><Schaltzeit><Schaltzeitpunkt>45</Schaltzeitpunkt><ZielSignalbild>gruen</ZielSignalbild></Schaltzeit><Schaltzeit><Schaltzeitpunkt>64</Schaltzeitpunkt><ZielSignalbild>rot</ZielSignalbild></Schaltzeit></SPZeile><SPZeile><Signalgruppe>K3</Signalgruppe><Schaltzeit><Schaltzeitpunkt>40</Schaltzeitpunkt><ZielSignalbild>rot</ZielSignalbild></Schaltzeit><Schaltzeit><Schaltzeitpunkt>70</Schaltzeitpunkt><ZielSignalbild>gruen</ZielSignalbild></Schaltzeit></SPZeile><SPZeile><Signalgruppe>KRi2</Signalgruppe><Schaltzeit><Schaltzeitpunkt>20</Schaltzeitpunkt><ZielSignalbild>gruen</ZielSignalbild></Schaltzeit><Schaltzeit><Schaltzeitpunkt>46</Schaltzeitpunkt><ZielSignalbild>dunkel</ZielSignalbild></Schaltzeit></SPZeile></Signalprogramm><Signalprogramm><Bezeichnung>SP 3 FZS Verkehrsschwach (50 s)</Bezeichnung><ObjNr>3</ObjNr><LetzteAenderung><Bearbeiter>trum_ja</Bearbeiter><Datum>2015-05-05T13:53:23.043Z</Datum></LetzteAenderung><Versatzzeitenmatrix>VMFA</Versatzzeitenmatrix><Versatzzeitenmatrix>VMFE</Versatzzeitenmatrix><OeVParameter>P1</OeVParameter><Typ><FZ>true</FZ><VA>false</VA></Typ><TU>50</TU><EP>5</EP><AP>7</AP><UP>6</UP><SignalzeitenVersatz>0</SignalzeitenVersatz><EProgramm>EP1 (22 s)</EProgramm><AProgramm>AP1 (26 s)</AProgramm><SPZeile><Signalgruppe>K1</Signalgruppe><Schaltzeit><Schaltzeitpunkt>19</Schaltzeitpunkt><ZielSignalbild>rot</ZielSignalbild></Schaltzeit><Schaltzeit><Schaltzeitpunkt>48</Schaltzeitpunkt><ZielSignalbild>gruen</ZielSignalbild></Schaltzeit></SPZeile><SPZeile><Signalgruppe>K2</Signalgruppe><Schaltzeit><Schaltzeitpunkt>27</Schaltzeitpunkt><ZielSignalbild>gruen</ZielSignalbild></Schaltzeit><Schaltzeit><Schaltzeitpunkt>42</Schaltzeitpunkt><ZielSignalbild>rot</ZielSignalbild></Schaltzeit></SPZeile><SPZeile><Signalgruppe>K3</Signalgruppe><Schaltzeit><Schaltzeitpunkt>22</Schaltzeitpunkt><ZielSignalbild>rot</ZielSignalbild></Schaltzeit><Schaltzeit><Schaltzeitpunkt>48</Schaltzeitpunkt><ZielSignalbild>gruen</ZielSignalbild></Schaltzeit></SPZeile><SPZeile><Signalgruppe>KRi2</Signalgruppe><DauerSignalbild>dunkel</DauerSignalbild></SPZeile></Signalprogramm><Signalprogramm><Bezeichnung>SP 5 FZS Handrast (44 s)</Bezeichnung><ObjNr>5</ObjNr><LetzteAenderung><Bearbeiter>trum_ja</Bearbeiter><Datum>2015-05-06T10:32:03.845Z</Datum></LetzteAenderung><Versatzzeitenmatrix>VMFA</Versatzzeitenmatrix><Versatzzeitenmatrix>VMFE</Versatzzeitenmatrix><OeVParameter>P1</OeVParameter><Typ><FZ>true</FZ><VA>false</VA></Typ><TU>44</TU><EP>5</EP><AP>7</AP><UP>6</UP><SignalzeitenVersatz>0</SignalzeitenVersatz><EProgramm>EP1 (22 s)</EProgramm><AProgramm>AP1 (26 s)</AProgramm><SPZeile><Signalgruppe>K1</Signalgruppe><Schaltzeit><Schaltzeitpunkt>10</Schaltzeitpunkt><ZielSignalbild>rot</ZielSignalbild></Schaltzeit><Schaltzeit><Schaltzeitpunkt>43</Schaltzeitpunkt><ZielSignalbild>gruen</ZielSignalbild></Schaltzeit></SPZeile><SPZeile><Signalgruppe>K2</Signalgruppe><Schaltzeit><Schaltzeitpunkt>26</Schaltzeitpunkt><ZielSignalbild>gruen</ZielSignalbild></Schaltzeit><Schaltzeit><Schaltzeitpunkt>37</Schaltzeitpunkt><ZielSignalbild>rot</ZielSignalbild></Schaltzeit></SPZeile><SPZeile><Signalgruppe>K3</Signalgruppe><Schaltzeit><Schaltzeitpunkt>21</Schaltzeitpunkt><ZielSignalbild>rot</ZielSignalbild></Schaltzeit><Schaltzeit><Schaltzeitpunkt>43</Schaltzeitpunkt><ZielSignalbild>gruen</ZielSignalbild></Schaltzeit></SPZeile><SPZeile><Signalgruppe>KRi2</Signalgruppe><Schaltzeit><Schaltzeitpunkt>16</Schaltzeitpunkt><ZielSignalbild>gruen</ZielSignalbild></Schaltzeit><Schaltzeit><Schaltzeitpunkt>27</Schaltzeitpunkt><ZielSignalbild>dunkel</ZielSignalbild></Schaltzeit></SPZeile></Signalprogramm><Signalprogramm><Bezeichnung>SP 11_PHAL (35 s)</Bezeichnung><ObjNr>11</ObjNr><LetzteAenderung><Bearbeiter>trum_ja</Bearbeiter><Datum>2015-05-06T10:32:53.663Z</Datum></LetzteAenderung><Versatzzeitenmatrix>VMFA</Versatzzeitenmatrix><Versatzzeitenmatrix>VMFE</Versatzzeitenmatrix><LogikParameterSatz>Satz_1</LogikParameterSatz><OeVParameter>P1</OeVParameter><Typ><FZ>false</FZ><VA>true</VA></Typ><TU>35</TU><UP>7</UP><SignalzeitenVersatz>0</SignalzeitenVersatz><EProgramm>EP1 (22 s)</EProgramm><AProgramm>AP1 (26 s)</AProgramm><SPZeile><Signalgruppe>K1</Signalgruppe><Schaltzeit><Schaltzeitpunkt>10</Schaltzeitpunkt><ZielSignalbild>rot</ZielSignalbild></Schaltzeit><Schaltzeit><Schaltzeitpunkt>34</Schaltzeitpunkt><ZielSignalbild>gruen</ZielSignalbild></Schaltzeit></SPZeile><SPZeile><Signalgruppe>K2</Signalgruppe><Schaltzeit><Schaltzeitpunkt>17</Schaltzeitpunkt><ZielSignalbild>gruen</ZielSignalbild></Schaltzeit><Schaltzeit><Schaltzeitpunkt>28</Schaltzeitpunkt><ZielSignalbild>rot</ZielSignalbild></Schaltzeit></SPZeile><SPZeile><Signalgruppe>K3</Signalgruppe><Schaltzeit><Schaltzeitpunkt>11</Schaltzeitpunkt><ZielSignalbild>rot</ZielSignalbild></Schaltzeit><Schaltzeit><Schaltzeitpunkt>34</Schaltzeitpunkt><ZielSignalbild>gruen</ZielSignalbild></Schaltzeit></SPZeile><SPZeile><Signalgruppe>KRi2</Signalgruppe><Schaltzeit><Schaltzeitpunkt>10</Schaltzeitpunkt><ZielSignalbild>gruen</ZielSignalbild></Schaltzeit><Schaltzeit><Schaltzeitpunkt>18</Schaltzeitpunkt><ZielSignalbild>dunkel</ZielSignalbild></Schaltzeit></SPZeile></Signalprogramm><Handprogramm><Signalprogramm>SP 5 FZS Handrast (44 s)</Signalprogramm><Standardsteuerung>true</Standardsteuerung></Handprogramm><Einschaltprogramm><Bezeichnung>EP1 (22 s)</Bezeichnung><ObjNr>12</ObjNr><LetzteAenderung><Bearbeiter>trum_ja</Bearbeiter><Datum>2015-05-05T14:10:56.005Z</Datum></LetzteAenderung><NurDoku>false</NurDoku><Dauer>22</Dauer><Signalsicherungszeitpunkt>0</Signalsicherungszeitpunkt><EAZeile><Signalgruppe>K1</Signalgruppe><Schaltzeit><Schaltzeitpunkt>11</Schaltzeitpunkt><Signalbild>gruen</Signalbild></Schaltzeit></EAZeile><EAZeile><Signalgruppe>K2</Signalgruppe><Schaltzeit><Schaltzeitpunkt>0</Schaltzeitpunkt><Signalbild>gelb</Signalbild></Schaltzeit><Schaltzeit><Schaltzeitpunkt>3</Schaltzeitpunkt><Signalbild>rot</Signalbild></Schaltzeit></EAZeile><EAZeile><Signalgruppe>K3</Signalgruppe><Schaltzeit><Schaltzeitpunkt>11</Schaltzeitpunkt><Signalbild>gruen</Signalbild></Schaltzeit></EAZeile><EAZeile><Signalgruppe>KRi2</Signalgruppe></EAZeile></Einschaltprogramm><Ausschaltprogramm><Bezeichnung>AP1 (26 s)</Bezeichnung><ObjNr>13</ObjNr><LetzteAenderung><Bearbeiter>trum_ja</Bearbeiter><Datum>2015-05-05T14:09:55.023Z</Datum></LetzteAenderung><NurDoku>false</NurDoku><Dauer>26</Dauer><Signalsicherungszeitpunkt>26</Signalsicherungszeitpunkt><EAZeile><Signalgruppe>K1</Signalgruppe><StartSignalbild>gruen</StartSignalbild><Schaltzeit><Schaltzeitpunkt>14</Schaltzeitpunkt><Signalbild>dunkel</Signalbild></Schaltzeit></EAZeile><EAZeile><Signalgruppe>K2</Signalgruppe><StartSignalbild>rot</StartSignalbild><Schaltzeit><Schaltzeitpunkt>25</Schaltzeitpunkt><Signalbild>gelbblk</Signalbild></Schaltzeit></EAZeile><EAZeile><Signalgruppe>K3</Signalgruppe><StartSignalbild>gruen</StartSignalbild><Schaltzeit><Schaltzeitpunkt>14</Schaltzeitpunkt><Signalbild>dunkel</Signalbild></Schaltzeit></EAZeile><EAZeile><Signalgruppe>KRi2</Signalgruppe><StartSignalbild>dunkel</StartSignalbild></EAZeile></Ausschaltprogramm></SignalprogrammListe><Teilknoten><Tk><Bezeichnung>TK 1</Bezeichnung><ObjNr>1</ObjNr></Tk><HardwareTk><Bezeichnung>LsaTK_1</Bezeichnung><ObjNr>1</ObjNr><Teilknoten>TK 1</Teilknoten></HardwareTk></Teilknoten><Unvertraeglichkeitsmatrix><Bezeichnung>UVM</Bezeichnung><Feind><SGr1>K1</SGr1><SGr2>K2</SGr2></Feind><Feind><SGr1>K1</SGr1><SGr2>KRi2</SGr2></Feind><Feind><SGr1>K2</SGr1><SGr2>K3</SGr2></Feind></Unvertraeglichkeitsmatrix><VersatzzeitenmatrixListe><Versatzzeitenmatrix><Bezeichnung>VMFA</Bezeichnung><ObjNr>1</ObjNr><Art>BeginnBeginn</Art></Versatzzeitenmatrix><Versatzzeitenmatrix><Bezeichnung>VMFE</Bezeichnung><ObjNr>2</ObjNr><Art>EndeEnde</Art></Versatzzeitenmatrix></VersatzzeitenmatrixListe><ZwischenzeitenmatrixListe><SicherheitsZwischenzeitenmatrix><Bezeichnung>ZZM</Bezeichnung><ObjNr>1</ObjNr><ZwiZt><Raeumer>K2</Raeumer><Einfahrer>K1</Einfahrer><T>5</T></ZwiZt><ZwiZt><Raeumer>KRi2</Raeumer><Einfahrer>K1</Einfahrer><T>4</T></ZwiZt><ZwiZt><Raeumer>K1</Raeumer><Einfahrer>K2</Einfahrer><T>6</T></ZwiZt><ZwiZt><Raeumer>K3</Raeumer><Einfahrer>K2</Einfahrer><T>6</T></ZwiZt><ZwiZt><Raeumer>K2</Raeumer><Einfahrer>K3</Einfahrer><T>6</T></ZwiZt><ZwiZt><Raeumer>K1</Raeumer><Einfahrer>KRi2</Einfahrer><T>6</T></ZwiZt></SicherheitsZwischenzeitenmatrix></ZwischenzeitenmatrixListe></Lichtsignalsteuerung_Versorgung>
